Workbook

Sheet Cover
A1: KO — Financial Model
A2: Source: Financial Modeling Prep API | All figures USD millions | FY 2021–2025
A4: Reporting Currency | B4: USD
A5: KEY METRICS — MOST RECENT YEAR
A6: Fiscal Year | B6: 2025
A7: Revenue ($mm) | B7: 47941
A8: Gross Profit ($mm) | B8: 29544
A9: EBITDA ($mm) | B9: 18702
A10: EBIT ($mm) | B10: 13762
A11: Net Income ($mm) | B11: 13107
A12: Free Cash Flow ($mm)
A13: EPS Diluted
A14: Gross Margin %
A15: EBITDA Margin %
A16: Net Margin %
A18: WORKBOOK STRUCTURE
A19: Cover | B19: This page — key metrics snapshot
A20: P&L | B20: Income statement: summary + all FMP line items
A21: Balance Sheet | B21: Balance sheet: summary + all FMP line items
A22: Cash Flow | B22: Cash flow: summary + all FMP line items
A23: Ratios & FCF | B23: UFCF bridge, LFCF bridge, and full ratio suite
A24: Segments | B24: Product & geographic revenue segments (plan-dependent)
A26: Colour convention: Blue = raw API data input | Black = formula/calculated | Green = cross-sheet link

Sheet P&L
A1: KO — Income Statement ($mm)
A2: All figures in USD millions. Blue = source data, Black = formula.
A3: Fiscal Year Ending | B3: 2021 | C3: 2022 | D3: 2023 | E3: 2024 | F3: 2025
A4: SUMMARY — INCOME STATEMENT
A5: (1) Revenue | B5: 38655 | C5: 43004 | D5: 45754 | E5: 47061 | F5: 47941
A6: (2) Cost of Revenue (COGS) | B6: 15357 | C6: 18000 | D6: 18520 | E6: 18324 | F6: 18397
A7: (3) Gross Profit | B7: =B5-B6 | C7: =C5-C6 | D7: =D5-D6 | E7: =E5-E6 | F7: =F5-F6
A8: Gross Margin % | B8: =IFERROR(B7/B5,"") | C8: =IFERROR(C7/C5,"") | D8: =IFERROR(D7/D5,"") | E8: =IFERROR(E7/E5,"") | F8: =IFERROR(F7/F5,"")
A9: (4) SG&A | B9: 11865 | C9: 12665 | D9: 13988 | E9: 14442 | F9: 14521
A10: (5) Other OPEX (ex-SG&A) | B10: =IFERROR(B11-B9,"") | C10: =IFERROR(C11-C9,"") | D10: =IFERROR(D11-D9,"") | E10: =IFERROR(E11-E9,"") | F10: =IFERROR(F11-F9,"")
A11: Total Operating Expenses | B11: 12990 | C11: 14095 | D11: 15923 | E11: 18745 | F11: 15782
A12: (6) EBITDA | B12: =B15+B14 | C12: =C15+C14 | D12: =D15+D14 | E12: =E15+E14 | F12: =F15+F14
A13: EBITDA Margin % | B13: =IFERROR(B12/B5,"") | C13: =IFERROR(C12/C5,"") | D13: =IFERROR(D12/D5,"") | E13: =IFERROR(E12/E5,"") | F13: =IFERROR(F12/F5,"")
A14: (7) Depreciation & Amortisation | B14: 1452 | C14: 1260 | D14: 1128 | E14: 1075 | F14: 1050
A15: (8) EBIT (Operating Income) | B15: 10308 | C15: 10909 | D15: 11311 | E15: 9992 | F15: 13762
A16: EBIT Margin % | B16: =IFERROR(B15/B5,"") | C16: =IFERROR(C15/C5,"") | D16: =IFERROR(D15/D5,"") | E16: =IFERROR(E15/E5,"") | F16: =IFERROR(F15/F5,"")
A17: Interest Expense | B17: 1597 | C17: 882 | D17: 1527 | E17: 1656 | F17: 1654
A18: Interest Income | B18: 276 | C18: 449 | D18: 907 | E18: 988 | F18: 786
A19: (9) Net Interest Income / (Expense) | B19: =IFERROR(B18-B17,"") | C19: =IFERROR(C18-C17,"") | D19: =IFERROR(D18-D17,"") | E19: =IFERROR(E18-E17,"") | F19: =IFERROR(F18-F17,"")
A20: Other Non-Operating Income / (Expenses) | B20: =IFERROR(B21-B15-B19,"") | C20: =IFERROR(C21-C15-C19,"") | D20: =IFERROR(D21-D15-D19,"") | E20: =IFERROR(E21-E15-E19,"") | F20: =IFERROR(F21-F15-F19,"")
A21: (10) EBT / NPBT | B21: 12425 | C21: 11686 | D21: 12952 | E21: 13086 | F21: 15998
A22: (11) Income Tax Expense | B22: 2621 | C22: 2115 | D22: 2249 | E22: 2437 | F22: 2861
A23: Effective Tax Rate % | B23: =IFERROR(B22/B21,"") | C23: =IFERROR(C22/C21,"") | D23: =IFERROR(D22/D21,"") | E23: =IFERROR(E22/E21,"") | F23: =IFERROR(F22/F21,"")
A24: (12) Net Income / NPAT | B24: 9771 | C24: 9542 | D24: 10714 | E24: 10631 | F24: 13107
A25: Net Margin % | B25: =IFERROR(B24/B5,"") | C25: =IFERROR(C24/C5,"") | D25: =IFERROR(D24/D5,"") | E25: =IFERROR(E24/E5,"") | F25: =IFERROR(F24/F5,"")
A27: DETAIL — ALL LINE ITEMS FROM FMP
A28: Fiscal Year Ending | B28: 2021 | C28: 2022 | D28: 2023 | E28: 2024 | F28: 2025
A29: Revenue & Cost
A30: Revenue | B30: 38655 | C30: 43004 | D30: 45754 | E30: 47061 | F30: 47941
A31: Cost of Revenue | B31: 15357 | C31: 18000 | D31: 18520 | E31: 18324 | F31: 18397
A32: Gross Profit | B32: 23298 | C32: 25004 | D32: 27234 | E32: 28737 | F32: 29544
A33: Operating Expenses
A34: R&D Expenses | B34: 0 | C34: 0 | D34: 0 | E34: 0 | F34: 0
A35: General & Administrative | B35: 7865 | C35: 8665 | D35: 8978 | E35: 9296 | F35: 9121
A36: Selling & Marketing | B36: 4000 | C36: 4000 | D36: 5010 | E36: 5146 | F36: 5400
A37: SG&A (Combined) | B37: 11865 | C37: 12665 | D37: 13988 | E37: 14442 | F37: 14521
A38: Other Expenses | B38: 1125 | C38: 1430 | D38: 1935 | E38: 4303 | F38: 1261
A39: Total Operating Expenses | B39: 12990 | C39: 14095 | D39: 15923 | E39: 18745 | F39: 15782
A40: Cost & Expenses (COGS + Opex) | B40: 28347 | C40: 32095 | D40: 34443 | E40: 37069 | F40: 34179
A41: Operating & EBITDA
A42: EBIT (Operating Income) | B42: 10308 | C42: 10909 | D42: 11311 | E42: 9992 | F42: 13762
A43: EBIT (FMP field) | B43: 14022 | C43: 12568 | D43: 14479 | E43: 14742 | F43: 17652
A44: EBITDA | B44: 15474 | C44: 13828 | D44: 15607 | E44: 15817 | F44: 18702
A45: Depreciation & Amortisation | B45: 1452 | C45: 1260 | D45: 1128 | E45: 1075 | F45: 1050
A46: Below the Line
A47: Interest Income | B47: 276 | C47: 449 | D47: 907 | E47: 988 | F47: 786
A48: Interest Expense | B48: 1597 | C48: 882 | D48: 1527 | E48: 1656 | F48: 1654
A49: Net Interest Income | B49: -1321 | C49: -433 | D49: -620 | E49: -668 | F49: -868
A50: Non-Operating Income (ex-interest) | B50: -3714 | C50: -1659 | D50: -3168 | E50: -4750 | F50: -3890
A51: Total Other Income / (Expenses) | B51: 2117 | C51: 777 | D51: 1641 | E51: 3094 | F51: 2236
A52: EBT / Income Before Tax | B52: 12425 | C52: 11686 | D52: 12952 | E52: 13086 | F52: 15998
A53: Income Tax Expense | B53: 2621 | C53: 2115 | D53: 2249 | E53: 2437 | F53: 2861
A54: Net Income
A55: Net Income from Continuing Ops | B55: 9804 | C55: 9571 | D55: 10703 | E55: 10649 | F55: 13137
A56: Net Income from Discontinued Ops | B56: 0 | C56: 0 | D56: 0 | E56: 0 | F56: 0
A57: Other Adjustments to Net Income | B57: 0 | C57: 0 | D57: 0 | E57: 0 | F57: 0
A58: Net Income Deductions | B58: 0 | C58: 0 | D58: 0 | E58: 0 | F58: 0
A59: Net Income | B59: 9771 | C59: 9542 | D59: 10714 | E59: 10631 | F59: 13107
A60: Bottom Line Net Income | B60: 9771 | C60: 9542 | D60: 10714 | E60: 10631 | F60: 13107
A61: Per Share
A62: EPS (Basic) | B62: 2.26 | C62: 2.2 | D62: 2.48 | E62: 2.47 | F62: 3.05
A63: EPS (Diluted)
A64: Shares Outstanding — Basic (mm) | B64: 4315 | C64: 4328 | D64: 4323 | E64: 4309 | F64: 4303
A65: Shares Outstanding — Diluted (mm) | B65: 4340 | C65: 4350 | D65: 4339 | E65: 4320 | F65: 4313
A66: Metadata
A67: Reported Currency | B67: USD | C67: USD | D67: USD | E67: USD | F67: USD

Sheet Balance Sheet
A1: KO — Balance Sheet ($mm)
A2: All figures in USD millions. Blue = source data, Black = formula.
A3: Fiscal Year Ending | B3: 2021 | C3: 2022 | D3: 2023 | E3: 2024 | F3: 2025
A4: SUMMARY — BALANCE SHEET
A5: (1) Cash & Cash Equivalents | B5: 9684 | C5: 9519 | D5: 9366 | E5: 10828 | F5: 10270
A6: (2) Receivables | B6: 3512 | C6: 3487 | D6: 3410 | E6: 3569 | F6: 3038
A7: (3) Inventory | B7: 3414 | C7: 4233 | D7: 4424 | E7: 4728 | F7: 4425
A8: (4) Other Current Assets | B8: =IFERROR(B9-B5-B6-B7,"") | C8: =IFERROR(C9-C5-C6-C7,"") | D8: =IFERROR(D9-D5-D6-D7,"") | E8: =IFERROR(E9-E5-E6-E7,"") | F8: =IFERROR(F9-F5-F6-F7,"")
A9: (5) Total Current Assets | B9: 22545 | C9: 22591 | D9: 26732 | E9: 25997 | F9: 31044
A10: (6) PP&E (Net) | B10: 9920 | C10: 9841 | D10: 9236 | E10: 11485 | F10: 9613
A11: (7) Goodwill | B11: 19363 | C11: 18782 | D11: 18358 | E11: 18139 | F11: 15491
A12: (8) Deferred Tax Assets | B12: 2129 | C12: 1746 | D12: 1561 | E12: 1319 | F12: 1206
A13: (9) Other LT Assets | B13: =IFERROR(B14-B10-B11-B12,"") | C13: =IFERROR(C14-C10-C11-C12,"") | D13: =IFERROR(D14-D10-D11-D12,"") | E13: =IFERROR(E14-E10-E11-E12,"") | F13: =IFERROR(F14-F10-F11-F12,"")
A14: (10) Total LT Assets | B14: 71809 | C14: 70172 | D14: 70971 | E14: 74552 | F14: 73772
A15: (11) Total Assets | B15: 94354 | C15: 92763 | D15: 97703 | E15: 100549 | F15: 104816
A17: (12) Accounts Payable | B17: 4602 | C17: 5307 | D17: 5590 | E17: 5468 | F17: 14813
A18: (13) Short-Term Borrowings | B18: 4955 | C18: 3113 | D18: 6878 | E18: 2437 | F18: 3373
A19: (14) Short-Term Leases
A20: (15) Other Current Liabilities | B20: =IFERROR(B21-B17-B18-B19,"") | C20: =IFERROR(C21-C17-C18-C19,"") | D20: =IFERROR(D21-D17-D18-D19,"") | E20: =IFERROR(E21-E17-E18-E19,"") | F20: =IFERROR(F21-F17-F18-F19,"")
A21: (16) Total Current Liabilities | B21: 19950 | C21: 19724 | D21: 23571 | E21: 25249 | F21: 21281
A22: (17) Long-Term Debt | B22: 38116 | C22: 36377 | D22: 35547 | E22: 42375 | F22: 42119
A23: (18) Long-Term Leases
A24: (19) Other LT Liabilities | B24: =IFERROR(B25-B21-B22-B23,"") | C24: =IFERROR(C25-C21-C22-C23,"") | D24: =IFERROR(D25-D21-D22-D23,"") | E24: =IFERROR(E25-E21-E22-E23,"") | F24: =IFERROR(F25-F21-F22-F23,"")
A25: (20) Total Liabilities | B25: 69494 | C25: 66937 | D25: 70223 | E25: 74177 | F25: 70541
A27: (21) Common Stock & APIC | B27: 1760 | C27: 1760 | D27: 1760 | E27: 1760 | F27: 1760
A28: (22) Retained Earnings | B28: 69094 | C28: 71019 | D28: 73782 | E28: 76054 | F28: 80382
A29: (23) Other Equity | B29: =IFERROR(B30-B27-B28,"") | C29: =IFERROR(C30-C27-C28,"") | D29: =IFERROR(D30-D27-D28,"") | E29: =IFERROR(E30-E27-E28,"") | F29: =IFERROR(F30-F27-F28,"")
A30: (24) Total Equity | B30: 22999 | C30: 24105 | D30: 25941 | E30: 24856 | F30: 32169
A31: (25) Total Liabilities & Equity | B31: =B25+B30 | C31: =C25+C30 | D31: =D25+D30 | E31: =E25+E30 | F31: =F25+F30
A33: DETAIL — ALL LINE ITEMS FROM FMP
A34: Fiscal Year Ending | B34: 2021 | C34: 2022 | D34: 2023 | E34: 2024 | F34: 2025
A35: Current Assets
A36: Cash & Cash Equivalents | B36: 9684 | C36: 9519 | D36: 9366 | E36: 10828 | F36: 10270
A37: Short-Term Investments | B37: 2941 | C37: 2112 | D37: 4297 | E37: 3743 | F37: 3602
A38: Cash & Short-Term Investments | B38: 12625 | C38: 11631 | D38: 13663 | E38: 14571 | F38: 13872
A39: Accounts Receivable (Trade) | B39: 3512 | C39: 3487 | D39: 3410 | E39: 3569 | F39: 3038
A40: Other Receivables | B40: 0 | C40: 0 | D40: 0 | E40: 0 | F40: 0
A41: Net Receivables (Total) | B41: 3512 | C41: 3487 | D41: 3410 | E41: 3569 | F41: 3038
A42: Inventory | B42: 3414 | C42: 4233 | D42: 4424 | E42: 4728 | F42: 4425
A43: Prepaids | B43: 0 | C43: 0 | D43: 0 | E43: 0 | F43: 0
A44: Other Current Assets | B44: 2994 | C44: 3240 | D44: 5235 | E44: 3129 | F44: 9709
A45: Total Current Assets | B45: 22545 | C45: 22591 | D45: 26732 | E45: 25997 | F45: 31044
A46: Non-Current Assets
A47: PP&E (Net) | B47: 9920 | C47: 9841 | D47: 9236 | E47: 11485 | F47: 9613
A48: Goodwill | B48: 19363 | C48: 18782 | D48: 18358 | E48: 18139 | F48: 15491
A49: Intangible Assets | B49: 15250 | C49: 14849 | D49: 14865 | E49: 13301 | F49: 12531
A50: Long-Term Investments | B50: 18416 | C50: 18765 | D50: 19789 | E50: 19275 | F50: 20235
A51: Tax Assets (Deferred) | B51: 2129 | C51: 1746 | D51: 1561 | E51: 1319 | F51: 1206
A52: Total Investments | B52: 21357 | C52: 20877 | D52: 24086 | E52: 23018 | F52: 23837
A53: Other Non-Current Assets | B53: 6731 | C53: 6189 | D53: 7162 | E53: 11033 | F53: 14696
A54: Total Non-Current Assets | B54: 71809 | C54: 70172 | D54: 70971 | E54: 74552 | F54: 73772
A55: TOTAL ASSETS | B55: 94354 | C55: 92763 | D55: 97703 | E55: 100549 | F55: 104816
A56: Current Liabilities
A57: Accounts Payable | B57: 4602 | C57: 5307 | D57: 5590 | E57: 5468 | F57: 14813
A58: Short-Term Debt | B58: 4955 | C58: 3113 | D58: 6878 | E58: 2437 | F58: 3373
A59: Short-Term Lease Liabilities
A60: Deferred Revenue (Current) | B60: 0 | C60: 0 | D60: 0 | E60: 0 | F60: 0
A61: Accrued & Other Current Liabilities | B61: 8656 | C61: 9014 | D61: 8069 | E61: 14492 | F61: 2570
A62: Other Current Liabilities | B62: =IFERROR(B63-B57-B58-B59-B60-B61,"") | C62: =IFERROR(C63-C57-C58-C59-C60-C61,"") | D62: =IFERROR(D63-D57-D58-D59-D60-D61,"") | E62: =IFERROR(E63-E57-E58-E59-E60-E61,"") | F62: =IFERROR(F63-F57-F58-F59-F60-F61,"")
A63: Total Current Liabilities | B63: 19950 | C63: 19724 | D63: 23571 | E63: 25249 | F63: 21281
A64: Non-Current Liabilities
A65: Long-Term Debt | B65: 38116 | C65: 36377 | D65: 35547 | E65: 42375 | F65: 42119
A66: Long-Term Operating Lease Liabilities
A67: Deferred Revenue (Non-Current) | B67: 0 | C67: 0 | D67: 0 | E67: 0 | F67: 0
A68: Deferred Tax Liabilities | B68: 2821 | C68: 2914 | D68: 2639 | E68: 2469 | F68: 2406
A69: Other Non-Current Liabilities | B69: 7446 | C69: 6809 | D69: 7465 | E69: 3161 | F69: 4735
A70: Total Non-Current Liabilities | B70: =IFERROR(B65+B66+B67+B68+B69,"") | C70: =IFERROR(C65+C66+C67+C68+C69,"") | D70: =IFERROR(D65+D66+D67+D68+D69,"") | E70: =IFERROR(E65+E66+E67+E68+E69,"") | F70: =IFERROR(F65+F66+F67+F68+F69,"")
A71: TOTAL LIABILITIES | B71: 69494 | C71: 66937 | D71: 70223 | E71: 74177 | F71: 70541
A72: Shareholders' Equity
A73: Common Stock & APIC | B73: 1760 | C73: 1760 | D73: 1760 | E73: 1760 | F73: 1760
A74: Retained Earnings | B74: 69094 | C74: 71019 | D74: 73782 | E74: 76054 | F74: 80382
A75: Other Total Stockholders Equity | B75: =IFERROR(B78-B73-B74-B77,"") | C75: =IFERROR(C78-C73-C74-C77,"") | D75: =IFERROR(D78-D73-D74-D77,"") | E75: =IFERROR(E78-E73-E74-E77,"") | F75: =IFERROR(F78-F73-F74-F77,"")
A76: Total Stockholders Equity | B76: =IFERROR(B73+B74+B75,"") | C76: =IFERROR(C73+C74+C75,"") | D76: =IFERROR(D73+D74+D75,"") | E76: =IFERROR(E73+E74+E75,"") | F76: =IFERROR(F73+F74+F75,"")
A77: Minority Interest | B77: 1861 | C77: 1721 | D77: 1539 | E77: 1516 | F77: 2106
A78: Total Equity (inc. Minority) | B78: 24860 | C78: 25826 | D78: 27480 | E78: 26372 | F78: 34275
A79: Key Derived Balances
A80: Total Debt (ST + LT) | B80: =B18+B22 | C80: =C18+C22 | D80: =D18+D22 | E80: =E18+E22 | F80: =F18+F22
A81: Net Debt | B81: =B80-B5 | C81: =C80-C5 | D81: =D80-D5 | E81: =E80-E5 | F81: =F80-F5
A82: Working Capital | B82: =IFERROR(B9-B21,"") | C82: =IFERROR(C9-C21,"") | D82: =IFERROR(D9-D21,"") | E82: =IFERROR(E9-E21,"") | F82: =IFERROR(F9-F21,"")
A83: TOTAL LIABILITIES & EQUITY | B83: =B31 | C83: =C31 | D83: =D31 | E83: =E31 | F83: =F31

Sheet Cash Flow
A1: KO — Cash Flow Statement ($mm)
A2: All figures in USD millions. Blue = source data, Black = formula.
A3: Fiscal Year Ending | B3: 2021 | C3: 2022 | D3: 2023 | E3: 2024 | F3: 2025
A4: SUMMARY — CASH FLOW STATEMENT
A5: (1) Net Cash from Operations (CFO) | B5: 12625 | C5: 11018 | D5: 11599 | E5: 6805 | F5: 7408
A6: (2) Capital Expenditures | B6: -1367 | C6: -1484 | D6: -1852 | E6: -2064 | F6: -2112
A7: (3) Net Cash from Investing (CFI) | B7: =B39 | C7: =C39 | D7: =D39 | E7: =E39 | F7: =F39
A9: (4) Debt Drawdowns | B9: 228 | C9: -958 | D9: 1857 | E9: 2528 | F9: 13
A10: (5) Debt Repayments
A11: (6) Issuance of Common Stock | B11: 702 | C11: 837 | D11: 539 | E11: 747 | F11: 313
A12: (7) Dividends Paid | B12: -7252 | C12: -7616 | D12: -7952 | E12: -8359 | F12: -8779
A13: (8) Net Cash from Financing (CFF) | B13: =B47 | C13: =C47 | D13: =D47 | E13: =E47 | F13: =F47
A15: Free Cash Flow (FCF) | B15: 11258 | C15: 9534 | D15: 9747 | E15: 4741 | F15: 5296
A16: Net Change in Cash | B16: 2915 | C16: -200 | D16: -133 | E16: 1796 | F16: -478
A18: DETAIL — ALL LINE ITEMS FROM FMP
A19: Fiscal Year Ending | B19: 2021 | C19: 2022 | D19: 2023 | E19: 2024 | F19: 2025
A20: Operating Activities
A21: Net Income | B21: 9804 | C21: 9571 | D21: 10714 | E21: 10631 | F21: 13107
A22: Depreciation & Amortisation | B22: 1452 | C22: 1260 | D22: 1128 | E22: 1075 | F22: 1050
A23: Deferred Income Tax | B23: 894 | C23: -122 | D23: -2 | E23: -11 | F23: 517
A24: Stock-Based Compensation | B24: 337 | C24: 356 | D24: 254 | E24: 286 | F24: 279
A25: Change in Working Capital | B25: 1325 | C25: -605 | D25: -846 | E25: -6234 | F25: -7208
A26: — Accounts Receivable | B26: -225 | C26: -69 | D26: -2 | E26: -295 | F26: 0
A27: — Inventory | B27: -135 | C27: -960 | D27: -597 | E27: -520 | F27: 0
A28: — Accounts Payable | B28: 2843 | C28: 759 | D28: 841 | E28: 1134 | F28: 0
A29: — Other Working Capital | B29: -1158 | C29: -335 | D29: -1088 | E29: -6553 | F29: -7208
A30: Other Non-Cash Items | B30: -1187 | C30: 558 | D30: 351 | E30: 1058 | F30: -367
A31: Net Cash from Operations (CFO) | B31: 12625 | C31: 11018 | D31: 11599 | E31: 6805 | F31: 7408
A32: Investing Activities
A33: Capital Expenditures | B33: -1367 | C33: -1484 | D33: -1852 | E33: -2064 | F33: -2112
A34: (Alt: Invest. in PP&E) | B34: -1367 | C34: -1484 | D34: -1852 | E34: -2064 | F34: -2112
A35: Acquisitions (Net) | B35: -2586 | C35: 385 | D35: 442 | E35: 3170 | F35: -461
A36: Purchases of Investments | B36: -6030 | C36: -3751 | D36: -6698 | E36: -5640 | F36: -6160
A37: Sales / Maturities of Investments | B37: 7059 | C37: 4771 | D37: 4354 | E37: 6589 | F37: 8232
A38: Other Investing Activities | B38: 159 | C38: -684 | D38: 405 | E38: 469 | F38: 434
A39: Net Cash from Investing (CFI) | B39: =IFERROR(B33+B35+B36+B37+B38,"") | C39: =IFERROR(C33+C35+C36+C37+C38,"") | D39: =IFERROR(D33+D35+D36+D37+D38,"") | E39: =IFERROR(E33+E35+E36+E37+E38,"") | F39: =IFERROR(F33+F35+F36+F37+F38,"")
A40: Financing Activities
A41: Debt Issuance (Net) | B41: 228 | C41: -958 | D41: 1857 | E41: 2528 | F41: 13
A42: Debt Repayment
A43: Common Stock Issuance | B43: 702 | C43: 837 | D43: 539 | E43: 747 | F43: 313
A44: Common Stock Repurchased (Buybacks) | B44: -111 | C44: -1418 | D44: -2289 | E44: -1795 | F44: -746
A45: Dividends Paid | B45: -7252 | C45: -7616 | D45: -7952 | E45: -8359 | F45: -8779
A46: Other Financing Activities | B46: -353 | C46: -1095 | D46: -465 | E46: -31 | F46: 1059
A47: Net Cash from Financing (CFF) | B47: =IFERROR(B41+B42+B43+B44+B45+B46,"") | C47: =IFERROR(C41+C42+C43+C44+C45+C46,"") | D47: =IFERROR(D41+D42+D43+D44+D45+D46,"") | E47: =IFERROR(E41+E42+E43+E44+E45+E46,"") | F47: =IFERROR(F41+F42+F43+F44+F45+F46,"")
A48: Cash Summary
A49: Effect of Forex on Cash | B49: -159 | C49: -205 | D49: -73 | E49: -623 | F49: 321
A50: Net Change in Cash | B50: 2915 | C50: -200 | D50: -133 | E50: 1796 | F50: -478
A51: Cash at Beginning of Period | B51: 7110 | C51: 10025 | D51: 9825 | E51: 9692 | F51: 11488
A52: Cash at End of Period | B52: 10025 | C52: 9825 | D52: 9692 | E52: 11488 | F52: 11010
A53: Free Cash Flow | B53: 11258 | C53: 9534 | D53: 9747 | E53: 4741 | F53: 5296
A54: Operating Cash Flow per Share
A55: Free Cash Flow per Share

Sheet Ratios & FCF
A1: KO — Key Ratios & Free Cash Flow Bridge
A2: All formulas. Black = calculated. Cross-sheet references pull from P&L, Balance Sheet, Cash Flow tabs.
A3: Fiscal Year Ending | B3: 2021 | C3: 2022 | D3: 2023 | E3: 2024 | F3: 2025
A4: UNLEVERED FREE CASH FLOW (UFCF) — STEP-BY-STEP BRIDGE
A5: Note: UFCF = NOPAT + D&A − ΔNWC − Capex | Used as input to DCF (unlevered / WACC-based)
A6: EBIT (Operating Income) | B6: ='P&L'!B15 | C6: ='P&L'!C15 | D6: ='P&L'!D15 | E6: ='P&L'!E15 | F6: ='P&L'!F15
A7: (−) Taxes on EBIT [EBIT × Eff. Tax Rate] | B7: =IFERROR(-B6*MAX(0,MIN(0.5,'P&L'!B22/'P&L'!B21)),0) | C7: =IFERROR(-C6*MAX(0,MIN(0.5,'P&L'!C22/'P&L'!C21)),0) | D7: =IFERROR(-D6*MAX(0,MIN(0.5,'P&L'!D22/'P&L'!D21)),0) | E7: =IFERROR(-E6*MAX(0,MIN(0.5,'P&L'!E22/'P&L'!E21)),0) | F7: =IFERROR(-F6*MAX(0,MIN(0.5,'P&L'!F22/'P&L'!F21)),0)
A8: NOPAT (Net Operating Profit After Tax) | B8: =B6+B7 | C8: =C6+C7 | D8: =D6+D7 | E8: =E6+E7 | F8: =F6+F7
A9: (+) Depreciation & Amortisation | B9: ='P&L'!B14 | C9: ='P&L'!C14 | D9: ='P&L'!D14 | E9: ='P&L'!E14 | F9: ='P&L'!F14
A10: = EBITDA (cross-check) | B10: =B8+B9 | C10: =C8+C9 | D10: =D8+D9 | E10: =E8+E9 | F10: =F8+F9
A11: (−) Increase in Net Working Capital [ΔRec + ΔInv − ΔAP] | B11: =0 | C11: =IFERROR(('Balance Sheet'!C6-'Balance Sheet'!B6)+('Balance Sheet'!C7-'Balance Sheet'!B7)-('Balance Sheet'!C17-'Balance Sheet'!B17),0) | D11: =IFERROR(('Balance Sheet'!D6-'Balance Sheet'!C6)+('Balance Sheet'!D7-'Balance Sheet'!C7)-('Balance Sheet'!D17-'Balance Sheet'!C17),0) | E11: =IFERROR(('Balance Sheet'!E6-'Balance Sheet'!D6)+('Balance Sheet'!E7-'Balance Sheet'!D7)-('Balance Sheet'!E17-'Balance Sheet'!D17),0) | F11: =IFERROR(('Balance Sheet'!F6-'Balance Sheet'!E6)+('Balance Sheet'!F7-'Balance Sheet'!E7)-('Balance Sheet'!F17-'Balance Sheet'!E17),0)
A12: (−) Capital Expenditures | B12: ='Cash Flow'!B6 | C12: ='Cash Flow'!C6 | D12: ='Cash Flow'!D6 | E12: ='Cash Flow'!E6 | F12: ='Cash Flow'!F6
A13: UNLEVERED FREE CASH FLOW (UFCF) | B13: =B8+B9-B11+B12 | C13: =C8+C9-C11+C12 | D13: =D8+D9-D11+D12 | E13: =E8+E9-E11+E12 | F13: =F8+F9-F11+F12
A14: UFCF Margin % | B14: =IFERROR(B13/'P&L'!B5,"") | C14: =IFERROR(C13/'P&L'!C5,"") | D14: =IFERROR(D13/'P&L'!D5,"") | E14: =IFERROR(E13/'P&L'!E5,"") | F14: =IFERROR(F13/'P&L'!F5,"")
A16: LEVERED FREE CASH FLOW (LFCF) — STEP-BY-STEP BRIDGE
A17: Note: LFCF = Net Income + D&A − ΔNWC − Capex | Represents cash available to equity holders
A18: Net Income | B18: ='P&L'!B24 | C18: ='P&L'!C24 | D18: ='P&L'!D24 | E18: ='P&L'!E24 | F18: ='P&L'!F24
A19: (+) Depreciation & Amortisation | B19: ='P&L'!B14 | C19: ='P&L'!C14 | D19: ='P&L'!D14 | E19: ='P&L'!E14 | F19: ='P&L'!F14
A20: (−) Increase in Net Working Capital | B20: =0 | C20: =IFERROR(('Balance Sheet'!C6-'Balance Sheet'!B6)+('Balance Sheet'!C7-'Balance Sheet'!B7)-('Balance Sheet'!C17-'Balance Sheet'!B17),0) | D20: =IFERROR(('Balance Sheet'!D6-'Balance Sheet'!C6)+('Balance Sheet'!D7-'Balance Sheet'!C7)-('Balance Sheet'!D17-'Balance Sheet'!C17),0) | E20: =IFERROR(('Balance Sheet'!E6-'Balance Sheet'!D6)+('Balance Sheet'!E7-'Balance Sheet'!D7)-('Balance Sheet'!E17-'Balance Sheet'!D17),0) | F20: =IFERROR(('Balance Sheet'!F6-'Balance Sheet'!E6)+('Balance Sheet'!F7-'Balance Sheet'!E7)-('Balance Sheet'!F17-'Balance Sheet'!E17),0)
A21: (−) Capital Expenditures | B21: ='Cash Flow'!B6 | C21: ='Cash Flow'!C6 | D21: ='Cash Flow'!D6 | E21: ='Cash Flow'!E6 | F21: ='Cash Flow'!F6
A22: LEVERED FREE CASH FLOW (LFCF) | B22: =B18+B19-B20+B21 | C22: =C18+C19-C20+C21 | D22: =D18+D19-D20+D21 | E22: =E18+E19-E20+E21 | F22: =F18+F19-F20+F21
A23: LFCF Margin % | B23: =IFERROR(B22/'P&L'!B5,"") | C23: =IFERROR(C22/'P&L'!C5,"") | D23: =IFERROR(D22/'P&L'!D5,"") | E23: =IFERROR(E22/'P&L'!E5,"") | F23: =IFERROR(F22/'P&L'!F5,"")
A24: FCF Conversion (LFCF / Net Income) | B24: =IFERROR(B22/B18,"") | C24: =IFERROR(C22/C18,"") | D24: =IFERROR(D22/D18,"") | E24: =IFERROR(E22/E18,"") | F24: =IFERROR(F22/F18,"")
A26: PROFITABILITY RATIOS
A27: Gross Margin % | B27: =IFERROR('P&L'!B7/'P&L'!B5,"") | C27: =IFERROR('P&L'!C7/'P&L'!C5,"") | D27: =IFERROR('P&L'!D7/'P&L'!D5,"") | E27: =IFERROR('P&L'!E7/'P&L'!E5,"") | F27: =IFERROR('P&L'!F7/'P&L'!F5,"")
A28: EBITDA Margin % | B28: =IFERROR('P&L'!B12/'P&L'!B5,"") | C28: =IFERROR('P&L'!C12/'P&L'!C5,"") | D28: =IFERROR('P&L'!D12/'P&L'!D5,"") | E28: =IFERROR('P&L'!E12/'P&L'!E5,"") | F28: =IFERROR('P&L'!F12/'P&L'!F5,"")
A29: EBIT Margin % | B29: =IFERROR('P&L'!B15/'P&L'!B5,"") | C29: =IFERROR('P&L'!C15/'P&L'!C5,"") | D29: =IFERROR('P&L'!D15/'P&L'!D5,"") | E29: =IFERROR('P&L'!E15/'P&L'!E5,"") | F29: =IFERROR('P&L'!F15/'P&L'!F5,"")
A30: Net Margin % | B30: =IFERROR('P&L'!B24/'P&L'!B5,"") | C30: =IFERROR('P&L'!C24/'P&L'!C5,"") | D30: =IFERROR('P&L'!D24/'P&L'!D5,"") | E30: =IFERROR('P&L'!E24/'P&L'!E5,"") | F30: =IFERROR('P&L'!F24/'P&L'!F5,"")
A31: Return on Equity (ROE) | B31: =IFERROR('P&L'!B24/'Balance Sheet'!B30,"") | C31: =IFERROR('P&L'!C24/'Balance Sheet'!C30,"") | D31: =IFERROR('P&L'!D24/'Balance Sheet'!D30,"") | E31: =IFERROR('P&L'!E24/'Balance Sheet'!E30,"") | F31: =IFERROR('P&L'!F24/'Balance Sheet'!F30,"")
A32: Return on Assets (ROA) | B32: =IFERROR('P&L'!B24/'Balance Sheet'!B15,"") | C32: =IFERROR('P&L'!C24/'Balance Sheet'!C15,"") | D32: =IFERROR('P&L'!D24/'Balance Sheet'!D15,"") | E32: =IFERROR('P&L'!E24/'Balance Sheet'!E15,"") | F32: =IFERROR('P&L'!F24/'Balance Sheet'!F15,"")
A33: ROIC [NOPAT / (Equity + Net Debt)] | B33: =IFERROR(('P&L'!B15*MAX(0,MIN(0.5,1-'P&L'!B22/'P&L'!B21)))/('Balance Sheet'!B30+'Balance Sheet'!B81),"") | C33: =IFERROR(('P&L'!C15*MAX(0,MIN(0.5,1-'P&L'!C22/'P&L'!C21)))/('Balance Sheet'!C30+'Balance Sheet'!C81),"") | D33: =IFERROR(('P&L'!D15*MAX(0,MIN(0.5,1-'P&L'!D22/'P&L'!D21)))/('Balance Sheet'!D30+'Balance Sheet'!D81),"") | E33: =IFERROR(('P&L'!E15*MAX(0,MIN(0.5,1-'P&L'!E22/'P&L'!E21)))/('Balance Sheet'!E30+'Balance Sheet'!E81),"") | F33: =IFERROR(('P&L'!F15*MAX(0,MIN(0.5,1-'P&L'!F22/'P&L'!F21)))/('Balance Sheet'!F30+'Balance Sheet'!F81),"")
A35: LEVERAGE & CREDIT RATIOS
A36: Net Debt / EBITDA | B36: =IFERROR(('Balance Sheet'!B22-'Balance Sheet'!B5)/'P&L'!B12,"") | C36: =IFERROR(('Balance Sheet'!C22-'Balance Sheet'!C5)/'P&L'!C12,"") | D36: =IFERROR(('Balance Sheet'!D22-'Balance Sheet'!D5)/'P&L'!D12,"") | E36: =IFERROR(('Balance Sheet'!E22-'Balance Sheet'!E5)/'P&L'!E12,"") | F36: =IFERROR(('Balance Sheet'!F22-'Balance Sheet'!F5)/'P&L'!F12,"")
A37: Total Debt / EBITDA | B37: =IFERROR('Balance Sheet'!B22/'P&L'!B12,"") | C37: =IFERROR('Balance Sheet'!C22/'P&L'!C12,"") | D37: =IFERROR('Balance Sheet'!D22/'P&L'!D12,"") | E37: =IFERROR('Balance Sheet'!E22/'P&L'!E12,"") | F37: =IFERROR('Balance Sheet'!F22/'P&L'!F12,"")
A38: Interest Coverage (EBIT / Interest Expense) | B38: =IFERROR('P&L'!B15/ABS('P&L'!B21-'P&L'!B15),"") | C38: =IFERROR('P&L'!C15/ABS('P&L'!C21-'P&L'!C15),"") | D38: =IFERROR('P&L'!D15/ABS('P&L'!D21-'P&L'!D15),"") | E38: =IFERROR('P&L'!E15/ABS('P&L'!E21-'P&L'!E15),"") | F38: =IFERROR('P&L'!F15/ABS('P&L'!F21-'P&L'!F15),"")
A39: Debt / Equity | B39: =IFERROR('Balance Sheet'!B22/'Balance Sheet'!B30,"") | C39: =IFERROR('Balance Sheet'!C22/'Balance Sheet'!C30,"") | D39: =IFERROR('Balance Sheet'!D22/'Balance Sheet'!D30,"") | E39: =IFERROR('Balance Sheet'!E22/'Balance Sheet'!E30,"") | F39: =IFERROR('Balance Sheet'!F22/'Balance Sheet'!F30,"")
A40: Total Debt / Total Assets | B40: =IFERROR('Balance Sheet'!B22/'Balance Sheet'!B15,"") | C40: =IFERROR('Balance Sheet'!C22/'Balance Sheet'!C15,"") | D40: =IFERROR('Balance Sheet'!D22/'Balance Sheet'!D15,"") | E40: =IFERROR('Balance Sheet'!E22/'Balance Sheet'!E15,"") | F40: =IFERROR('Balance Sheet'!F22/'Balance Sheet'!F15,"")
A42: LIQUIDITY RATIOS
A43: Current Ratio (CA / CL) | B43: =IFERROR('Balance Sheet'!B9/'Balance Sheet'!B21,"") | C43: =IFERROR('Balance Sheet'!C9/'Balance Sheet'!C21,"") | D43: =IFERROR('Balance Sheet'!D9/'Balance Sheet'!D21,"") | E43: =IFERROR('Balance Sheet'!E9/'Balance Sheet'!E21,"") | F43: =IFERROR('Balance Sheet'!F9/'Balance Sheet'!F21,"")
A44: Quick Ratio (CA − Inventory) / CL | B44: =IFERROR(('Balance Sheet'!B9-'Balance Sheet'!B7)/'Balance Sheet'!B21,"") | C44: =IFERROR(('Balance Sheet'!C9-'Balance Sheet'!C7)/'Balance Sheet'!C21,"") | D44: =IFERROR(('Balance Sheet'!D9-'Balance Sheet'!D7)/'Balance Sheet'!D21,"") | E44: =IFERROR(('Balance Sheet'!E9-'Balance Sheet'!E7)/'Balance Sheet'!E21,"") | F44: =IFERROR(('Balance Sheet'!F9-'Balance Sheet'!F7)/'Balance Sheet'!F21,"")
A45: Cash Ratio (Cash / CL) | B45: =IFERROR('Balance Sheet'!B5/'Balance Sheet'!B21,"") | C45: =IFERROR('Balance Sheet'!C5/'Balance Sheet'!C21,"") | D45: =IFERROR('Balance Sheet'!D5/'Balance Sheet'!D21,"") | E45: =IFERROR('Balance Sheet'!E5/'Balance Sheet'!E21,"") | F45: =IFERROR('Balance Sheet'!F5/'Balance Sheet'!F21,"")
A47: EFFICIENCY & WORKING CAPITAL
A48: Asset Turnover (Revenue / Assets) | B48: =IFERROR('P&L'!B5/'Balance Sheet'!B15,"") | C48: =IFERROR('P&L'!C5/'Balance Sheet'!C15,"") | D48: =IFERROR('P&L'!D5/'Balance Sheet'!D15,"") | E48: =IFERROR('P&L'!E5/'Balance Sheet'!E15,"") | F48: =IFERROR('P&L'!F5/'Balance Sheet'!F15,"")
A49: Receivables Days (Avg Rec / Rev × 365) | B49: =IFERROR('Balance Sheet'!B6/'P&L'!B5*365,"") | C49: =IFERROR(AVERAGE('Balance Sheet'!C6,'Balance Sheet'!B6)/'P&L'!C5*365,"") | D49: =IFERROR(AVERAGE('Balance Sheet'!D6,'Balance Sheet'!C6)/'P&L'!D5*365,"") | E49: =IFERROR(AVERAGE('Balance Sheet'!E6,'Balance Sheet'!D6)/'P&L'!E5*365,"") | F49: =IFERROR(AVERAGE('Balance Sheet'!F6,'Balance Sheet'!E6)/'P&L'!F5*365,"")
A50: Inventory Days (Avg Inv / COGS × 365) | B50: =IFERROR('Balance Sheet'!B7/'P&L'!B6*365,"") | C50: =IFERROR(AVERAGE('Balance Sheet'!C7,'Balance Sheet'!B7)/'P&L'!C6*365,"") | D50: =IFERROR(AVERAGE('Balance Sheet'!D7,'Balance Sheet'!C7)/'P&L'!D6*365,"") | E50: =IFERROR(AVERAGE('Balance Sheet'!E7,'Balance Sheet'!D7)/'P&L'!E6*365,"") | F50: =IFERROR(AVERAGE('Balance Sheet'!F7,'Balance Sheet'!E7)/'P&L'!F6*365,"")
A51: Payables Days (Avg AP / COGS × 365) | B51: =IFERROR('Balance Sheet'!B17/'P&L'!B6*365,"") | C51: =IFERROR(AVERAGE('Balance Sheet'!C17,'Balance Sheet'!B17)/'P&L'!C6*365,"") | D51: =IFERROR(AVERAGE('Balance Sheet'!D17,'Balance Sheet'!C17)/'P&L'!D6*365,"") | E51: =IFERROR(AVERAGE('Balance Sheet'!E17,'Balance Sheet'!D17)/'P&L'!E6*365,"") | F51: =IFERROR(AVERAGE('Balance Sheet'!F17,'Balance Sheet'!E17)/'P&L'!F6*365,"")
A52: Cash Conversion Cycle (Rec Days + Inv Days − AP Days) | B52: =IFERROR(B49+B50-B51,"") | C52: =IFERROR(C49+C50-C51,"") | D52: =IFERROR(D49+D50-D51,"") | E52: =IFERROR(E49+E50-E51,"") | F52: =IFERROR(F49+F50-F51,"")
A54: CASH FLOW QUALITY
A55: FCF Margin (FCF / Revenue) | B55: =IFERROR('Cash Flow'!B15/'P&L'!B5,"") | C55: =IFERROR('Cash Flow'!C15/'P&L'!C5,"") | D55: =IFERROR('Cash Flow'!D15/'P&L'!D5,"") | E55: =IFERROR('Cash Flow'!E15/'P&L'!E5,"") | F55: =IFERROR('Cash Flow'!F15/'P&L'!F5,"")
A56: FCF Conversion (FCF / Net Income) | B56: =IFERROR('Cash Flow'!B15/'P&L'!B24,"") | C56: =IFERROR('Cash Flow'!C15/'P&L'!C24,"") | D56: =IFERROR('Cash Flow'!D15/'P&L'!D24,"") | E56: =IFERROR('Cash Flow'!E15/'P&L'!E24,"") | F56: =IFERROR('Cash Flow'!F15/'P&L'!F24,"")
A57: Capex as % of Revenue | B57: =IFERROR(ABS('Cash Flow'!B6)/'P&L'!B5,"") | C57: =IFERROR(ABS('Cash Flow'!C6)/'P&L'!C5,"") | D57: =IFERROR(ABS('Cash Flow'!D6)/'P&L'!D5,"") | E57: =IFERROR(ABS('Cash Flow'!E6)/'P&L'!E5,"") | F57: =IFERROR(ABS('Cash Flow'!F6)/'P&L'!F5,"")
A58: CFO / Net Income (Cash Quality) | B58: =IFERROR('Cash Flow'!B5/'P&L'!B24,"") | C58: =IFERROR('Cash Flow'!C5/'P&L'!C24,"") | D58: =IFERROR('Cash Flow'!D5/'P&L'!D24,"") | E58: =IFERROR('Cash Flow'!E5/'P&L'!E24,"") | F58: =IFERROR('Cash Flow'!F5/'P&L'!F24,"")
A60: PER SHARE METRICS
A61: Diluted Shares (mm) | B61: 4340 | C61: 4350 | D61: 4339 | E61: 4320 | F61: 4313
A62: FCF per Share | B62: =IFERROR('Cash Flow'!B15/'Ratios & FCF'!B61,"") | C62: =IFERROR('Cash Flow'!C15/'Ratios & FCF'!C61,"") | D62: =IFERROR('Cash Flow'!D15/'Ratios & FCF'!D61,"") | E62: =IFERROR('Cash Flow'!E15/'Ratios & FCF'!E61,"") | F62: =IFERROR('Cash Flow'!F15/'Ratios & FCF'!F61,"")
A63: Book Value per Share | B63: =IFERROR('Balance Sheet'!B30/'Ratios & FCF'!B61,"") | C63: =IFERROR('Balance Sheet'!C30/'Ratios & FCF'!C61,"") | D63: =IFERROR('Balance Sheet'!D30/'Ratios & FCF'!D61,"") | E63: =IFERROR('Balance Sheet'!E30/'Ratios & FCF'!E61,"") | F63: =IFERROR('Balance Sheet'!F30/'Ratios & FCF'!F61,"")
A65: MODEL CONTROLS — KEY RECONCILIATION CHECKS
A66: Zero = OK | Non-zero = investigate | Blank = FMP returned no data for that field
A67: MASTER CHECK — ALL CONTROLS | B67: =IF((IFERROR((ABS(B70)>0.01)*1,0)+IFERROR((ABS(B71)>0.01)*1,0)+IFERROR((ABS(B73)>0.01)*1,0)+IFERROR((ABS(B75)>0.01)*1,0)+IFERROR((ABS(B76)>0.01)*1,0)+IFERROR((ABS(B78)>0.01)*1,0)+IFERROR((ABS(B79)>0.01)*1,0))=0,"ALL PASS","FAIL: "&(IFERROR((ABS(B70)>0.01)*1,0)+IFERROR((ABS(B71)>0.01)*1,0)+IFERROR((ABS(B73)>0.01)*1,0)+IFERROR((ABS(B75)>0.01)*1,0)+IFERROR((ABS(B76)>0.01)*1,0)+IFERROR((ABS(B78)>0.01)*1,0)+IFERROR((ABS(B79)>0.01)*1,0))&" check(s) non-zero") | C67: =IF((IFERROR((ABS(C70)>0.01)*1,0)+IFERROR((ABS(C71)>0.01)*1,0)+IFERROR((ABS(C73)>0.01)*1,0)+IFERROR((ABS(C75)>0.01)*1,0)+IFERROR((ABS(C76)>0.01)*1,0)+IFERROR((ABS(C78)>0.01)*1,0)+IFERROR((ABS(C79)>0.01)*1,0))=0,"ALL PASS","FAIL: "&(IFERROR((ABS(C70)>0.01)*1,0)+IFERROR((ABS(C71)>0.01)*1,0)+IFERROR((ABS(C73)>0.01)*1,0)+IFERROR((ABS(C75)>0.01)*1,0)+IFERROR((ABS(C76)>0.01)*1,0)+IFERROR((ABS(C78)>0.01)*1,0)+IFERROR((ABS(C79)>0.01)*1,0))&" check(s) non-zero") | D67: =IF((IFERROR((ABS(D70)>0.01)*1,0)+IFERROR((ABS(D71)>0.01)*1,0)+IFERROR((ABS(D73)>0.01)*1,0)+IFERROR((ABS(D75)>0.01)*1,0)+IFERROR((ABS(D76)>0.01)*1,0)+IFERROR((ABS(D78)>0.01)*1,0)+IFERROR((ABS(D79)>0.01)*1,0))=0,"ALL PASS","FAIL: "&(IFERROR((ABS(D70)>0.01)*1,0)+IFERROR((ABS(D71)>0.01)*1,0)+IFERROR((ABS(D73)>0.01)*1,0)+IFERROR((ABS(D75)>0.01)*1,0)+IFERROR((ABS(D76)>0.01)*1,0)+IFERROR((ABS(D78)>0.01)*1,0)+IFERROR((ABS(D79)>0.01)*1,0))&" check(s) non-zero") | E67: =IF((IFERROR((ABS(E70)>0.01)*1,0)+IFERROR((ABS(E71)>0.01)*1,0)+IFERROR((ABS(E73)>0.01)*1,0)+IFERROR((ABS(E75)>0.01)*1,0)+IFERROR((ABS(E76)>0.01)*1,0)+IFERROR((ABS(E78)>0.01)*1,0)+IFERROR((ABS(E79)>0.01)*1,0))=0,"ALL PASS","FAIL: "&(IFERROR((ABS(E70)>0.01)*1,0)+IFERROR((ABS(E71)>0.01)*1,0)+IFERROR((ABS(E73)>0.01)*1,0)+IFERROR((ABS(E75)>0.01)*1,0)+IFERROR((ABS(E76)>0.01)*1,0)+IFERROR((ABS(E78)>0.01)*1,0)+IFERROR((ABS(E79)>0.01)*1,0))&" check(s) non-zero") | F67: =IF((IFERROR((ABS(F70)>0.01)*1,0)+IFERROR((ABS(F71)>0.01)*1,0)+IFERROR((ABS(F73)>0.01)*1,0)+IFERROR((ABS(F75)>0.01)*1,0)+IFERROR((ABS(F76)>0.01)*1,0)+IFERROR((ABS(F78)>0.01)*1,0)+IFERROR((ABS(F79)>0.01)*1,0))=0,"ALL PASS","FAIL: "&(IFERROR((ABS(F70)>0.01)*1,0)+IFERROR((ABS(F71)>0.01)*1,0)+IFERROR((ABS(F73)>0.01)*1,0)+IFERROR((ABS(F75)>0.01)*1,0)+IFERROR((ABS(F76)>0.01)*1,0)+IFERROR((ABS(F78)>0.01)*1,0)+IFERROR((ABS(F79)>0.01)*1,0))&" check(s) non-zero")
A69: P&L Checks
A70: Gross Profit: (Revenue - COGS) vs Reported [= 0] | B70: =IFERROR('P&L'!B5-'P&L'!B6-'P&L'!B7,"") | C70: =IFERROR('P&L'!C5-'P&L'!C6-'P&L'!C7,"") | D70: =IFERROR('P&L'!D5-'P&L'!D6-'P&L'!D7,"") | E70: =IFERROR('P&L'!E5-'P&L'!E6-'P&L'!E7,"") | F70: =IFERROR('P&L'!F5-'P&L'!F6-'P&L'!F7,"")
A71: EBITDA: (EBIT + D&A) vs Reported [= 0 — formula-driven, always passes] | B71: =IFERROR('P&L'!B15+'P&L'!B14-'P&L'!B12,"") | C71: =IFERROR('P&L'!C15+'P&L'!C14-'P&L'!C12,"") | D71: =IFERROR('P&L'!D15+'P&L'!D14-'P&L'!D12,"") | E71: =IFERROR('P&L'!E15+'P&L'!E14-'P&L'!E12,"") | F71: =IFERROR('P&L'!F15+'P&L'!F14-'P&L'!F12,"")
A72: Below-the-Line Residual: (EBT - EBIT) - Net Interest [non-zero = Other Non-Op items, informational] | B72: =IFERROR(('P&L'!B21-'P&L'!B15)-('P&L'!B18-'P&L'!B17),"") | C72: =IFERROR(('P&L'!C21-'P&L'!C15)-('P&L'!C18-'P&L'!C17),"") | D72: =IFERROR(('P&L'!D21-'P&L'!D15)-('P&L'!D18-'P&L'!D17),"") | E72: =IFERROR(('P&L'!E21-'P&L'!E15)-('P&L'!E18-'P&L'!E17),"") | F72: =IFERROR(('P&L'!F21-'P&L'!F15)-('P&L'!F18-'P&L'!F17),"")
A73: Net Income: (EBT - Tax) vs Reported [= 0] | B73: =IFERROR('P&L'!B21-'P&L'!B22-'P&L'!B24,"") | C73: =IFERROR('P&L'!C21-'P&L'!C22-'P&L'!C24,"") | D73: =IFERROR('P&L'!D21-'P&L'!D22-'P&L'!D24,"") | E73: =IFERROR('P&L'!E21-'P&L'!E22-'P&L'!E24,"") | F73: =IFERROR('P&L'!F21-'P&L'!F22-'P&L'!F24,"")
A74: Balance Sheet Checks
A75: BS Balanced: Total Assets vs (Total Liabilities + Total Equity) [= 0] | B75: =IFERROR('Balance Sheet'!B15-'Balance Sheet'!B25-'Balance Sheet'!B30,"") | C75: =IFERROR('Balance Sheet'!C15-'Balance Sheet'!C25-'Balance Sheet'!C30,"") | D75: =IFERROR('Balance Sheet'!D15-'Balance Sheet'!D25-'Balance Sheet'!D30,"") | E75: =IFERROR('Balance Sheet'!E15-'Balance Sheet'!E25-'Balance Sheet'!E30,"") | F75: =IFERROR('Balance Sheet'!F15-'Balance Sheet'!F25-'Balance Sheet'!F30,"")
A76: Assets: (Total CA + Total LT Assets) vs Total Assets [= 0] | B76: =IFERROR('Balance Sheet'!B9+('Balance Sheet'!B14)-'Balance Sheet'!B15,"") | C76: =IFERROR('Balance Sheet'!C9+('Balance Sheet'!C14)-'Balance Sheet'!C15,"") | D76: =IFERROR('Balance Sheet'!D9+('Balance Sheet'!D14)-'Balance Sheet'!D15,"") | E76: =IFERROR('Balance Sheet'!E9+('Balance Sheet'!E14)-'Balance Sheet'!E15,"") | F76: =IFERROR('Balance Sheet'!F9+('Balance Sheet'!F14)-'Balance Sheet'!F15,"")
A77: Cash Flow Checks
A78: Cash Change: CFO + CFI + CFF vs Reported Net Change [= 0] | B78: =IFERROR('Cash Flow'!B5+'Cash Flow'!B7+'Cash Flow'!B13-'Cash Flow'!B50,"") | C78: =IFERROR('Cash Flow'!C5+'Cash Flow'!C7+'Cash Flow'!C13-'Cash Flow'!C50,"") | D78: =IFERROR('Cash Flow'!D5+'Cash Flow'!D7+'Cash Flow'!D13-'Cash Flow'!D50,"") | E78: =IFERROR('Cash Flow'!E5+'Cash Flow'!E7+'Cash Flow'!E13-'Cash Flow'!E50,"") | F78: =IFERROR('Cash Flow'!F5+'Cash Flow'!F7+'Cash Flow'!F13-'Cash Flow'!F50,"")
A79: FCF: (CFO + Capex) vs Reported FCF [= 0] | B79: =IFERROR('Cash Flow'!B5+'Cash Flow'!B6-'Cash Flow'!B15,"") | C79: =IFERROR('Cash Flow'!C5+'Cash Flow'!C6-'Cash Flow'!C15,"") | D79: =IFERROR('Cash Flow'!D5+'Cash Flow'!D6-'Cash Flow'!D15,"") | E79: =IFERROR('Cash Flow'!E5+'Cash Flow'!E6-'Cash Flow'!E15,"") | F79: =IFERROR('Cash Flow'!F5+'Cash Flow'!F6-'Cash Flow'!F15,"")
A80: UFCF Bridge Check [informational — not exact]
A81: UFCF vs (CFO + Capex) [difference = NWC and tax adjustments] | B81: =IFERROR(B13-('Cash Flow'!B5+'Cash Flow'!B6),"") | C81: =IFERROR(C13-('Cash Flow'!C5+'Cash Flow'!C6),"") | D81: =IFERROR(D13-('Cash Flow'!D5+'Cash Flow'!D6),"") | E81: =IFERROR(E13-('Cash Flow'!E5+'Cash Flow'!E6),"") | F81: =IFERROR(F13-('Cash Flow'!F5+'Cash Flow'!F6),"")

Sheet Segments
A1: KO — Revenue Segmentation
A2: Requires FMP Starter plan or above. Data sourced from company filings.
A3: PRODUCT / BUSINESS SEGMENT REVENUE ($mm)
A4: Fiscal Year Ending | B4: 2025 | C4: 2024 | D4: 2023 | E4: 2022 | F4: 2021
A5: data | B5: 31558 | C5: 38776 | D5: 7860 | E5: 7891 | F5: 7203
A8: GEOGRAPHIC SEGMENT REVENUE ($mm)
A9: Data not available on your current FMP plan (requires Starter or above). Upgrade at financialmodelingprep.com to unlock segment data.

Sheet WACC
A1: KO — WACC & COST OF CAPITAL
A2: Blue = user override | Green = selected input | Default pre-filled with average of all sources | All figures USD millions
A4: CAPITAL STRUCTURE
A5: Equity (market capitalisation, $mm) | B5: 350566.27 | C5: FMP marketCap | price $81.48
A6: Debt (gross book value, $mm) | B6: 45492 | C6: FMP: shortTermDebt + longTermDebt, most recent yr-end
A7: Total capital (V = E + D) | B7: =B5+B6
A8: Equity weight (E / V) | B8: =IFERROR(B5/B7,1) | C8: Weight applied to Re in WACC
A9: Debt weight (D / V) | B9: =IFERROR(B6/B7,0) | C9: Weight applied to after-tax Rd in WACC
A11: STEP 1 — RISK-FREE RATE
A12: 10-yr US Treasury yield (FRED DGS10) | B12: 0.0456 | C12: FRED series DGS10 | latest: 2026-05-22
A13: ► Selected Rf (override if needed) | B13: 0.0456 | C13: Pre-filled with live FRED DGS10 rate
A15: STEP 2 — BETA
A16: Raw beta (FMP — 5yr monthly vs S&P 500) | B16: 0.356 | C16: FMP company profile endpoint
A17: Blume-adjusted (0.67 × raw + 0.33) | B17: 0.569 | C17: Mean-reversion toward market beta of 1.0
A18: Damodaran industry unlevered (Beverages - Non-Alcoholic) | B18: 1 | C18: Damodaran.com — betas by industry, Jan 2025 US
A19: Damodaran re-levered (D/E = 0.13x, t = 17.9%) | B19: 1.107 | C19: =unlevered × (1 + (1 − t) × D/E)
A20: ► Selected beta (user override) | B20: 0.677 | C20: Default = average of 3 source(s) above — override freely
A22: STEP 3 — EQUITY RISK PREMIUM (ERP)
A23: Damodaran implied ERP — US market (current) | B23: 0.0472 | C23: Damodaran.com implied ERP — Jan 2026
A24: Damodaran historical avg — US 1928–2025 | B24: 0.042 | C24: Arithmetic average excess return over T-bill
A25: ► Selected ERP (user override) | B25: 0.0446 | C25: Default = average of Damodaran implied & historical avg — override freely
A27: STEP 4 — COST OF EQUITY (CAPM: Re = Rf + β × ERP)
A28: Cost of equity (Re) | B28: =B13+B20*B25 | C28: CAPM formula — references selected inputs above
A30: STEP 5 — COST OF DEBT (Pre-tax Rd)
A31: Credit rating (S&P / Moody's) | B31: A+ | C31: User input
A32: FRED matched yield (rating-tier index) | B32: 0.0507 | C32: FRED BAMLC0A3CAEY — A
A33: Interest Coverage Ratio (EBIT / Gross Int Exp) | B33: 8.3 | C33: EBIT $13762mm / Int Exp $1654mm
A34: Synthetic rating (Damodaran ICR table) | B34: A+ | C34: ICR 8.3x → A+
A35: Synthetic Rd (Rf + Damodaran default spread) | B35: 0.0552 | C35: Rf 4.56% + spread 0.96%
A36: Accounting Rd (Gross int exp / Avg gross debt) | B36: 0.036631821 | C36: Cross-check only — backward-looking
A37: ► Selected pre-tax Rd (user override) | B37: 0.0475 | C37: Default = average of 3 source(s) above — override freely
A39: STEP 6 — TAX RATE
A40: Effective tax rate (tax expense / pre-tax income) | B40: 0.1788 | C40: FMP: $2861mm / $15998mm
A41: ► Selected tax rate (user override) | B41: 0.1788 | C41: Adjust to normalised / marginal rate if preferred
A43: WACC OUTPUT
A44: WACC = MAX(8.5%, (E/V × Re) + (D/V × Rd × (1 − t))) | B44: =MAX(0.085, B8*B28+B9*B37*(1-B41)) | C44: Floored 8.5% (D-001); raw formula below
A46: SENSITIVITY — WACC (%) by Beta offset × ERP offset
A47: Beta offset \ ERP offset → | B47: -1.0% | C47: -0.5% | D47: Base ERP | E47: +0.5% | F47: +1.0%
A48: -1.0 | B48: =B8*(B13+(B20+(-1.0))*(B25+(-0.01)))+B9*B37*(1-B41) | C48: =B8*(B13+(B20+(-1.0))*(B25+(-0.005)))+B9*B37*(1-B41) | D48: =B8*(B13+(B20+(-1.0))*(B25+(0.0)))+B9*B37*(1-B41) | E48: =B8*(B13+(B20+(-1.0))*(B25+(0.005)))+B9*B37*(1-B41) | F48: =B8*(B13+(B20+(-1.0))*(B25+(0.01)))+B9*B37*(1-B41)
A49: -0.5 | B49: =B8*(B13+(B20+(-0.5))*(B25+(-0.01)))+B9*B37*(1-B41) | C49: =B8*(B13+(B20+(-0.5))*(B25+(-0.005)))+B9*B37*(1-B41) | D49: =B8*(B13+(B20+(-0.5))*(B25+(0.0)))+B9*B37*(1-B41) | E49: =B8*(B13+(B20+(-0.5))*(B25+(0.005)))+B9*B37*(1-B41) | F49: =B8*(B13+(B20+(-0.5))*(B25+(0.01)))+B9*B37*(1-B41)
A50: Base β | B50: =B8*(B13+(B20+(0.0))*(B25+(-0.01)))+B9*B37*(1-B41) | C50: =B8*(B13+(B20+(0.0))*(B25+(-0.005)))+B9*B37*(1-B41) | D50: =B8*(B13+(B20+(0.0))*(B25+(0.0)))+B9*B37*(1-B41) | E50: =B8*(B13+(B20+(0.0))*(B25+(0.005)))+B9*B37*(1-B41) | F50: =B8*(B13+(B20+(0.0))*(B25+(0.01)))+B9*B37*(1-B41)
A51: +0.5 | B51: =B8*(B13+(B20+(0.5))*(B25+(-0.01)))+B9*B37*(1-B41) | C51: =B8*(B13+(B20+(0.5))*(B25+(-0.005)))+B9*B37*(1-B41) | D51: =B8*(B13+(B20+(0.5))*(B25+(0.0)))+B9*B37*(1-B41) | E51: =B8*(B13+(B20+(0.5))*(B25+(0.005)))+B9*B37*(1-B41) | F51: =B8*(B13+(B20+(0.5))*(B25+(0.01)))+B9*B37*(1-B41)
A52: +1.0 | B52: =B8*(B13+(B20+(1.0))*(B25+(-0.01)))+B9*B37*(1-B41) | C52: =B8*(B13+(B20+(1.0))*(B25+(-0.005)))+B9*B37*(1-B41) | D52: =B8*(B13+(B20+(1.0))*(B25+(0.0)))+B9*B37*(1-B41) | E52: =B8*(B13+(B20+(1.0))*(B25+(0.005)))+B9*B37*(1-B41) | F52: =B8*(B13+(B20+(1.0))*(B25+(0.01)))+B9*B37*(1-B41)

Sheet DCF
A1: KO — DCF VALUATION
A2: Grey = historical actual | Blue (darker) = FMP analyst consensus | Blue (lighter) = user input | Amber = key assumption
A3: Fiscal Year | B3: 2021 | C3: 2022 | D3: 2023 | E3: 2024 | F3: 2025 | G3: 2026E | H3: 2027E | I3: 2028E | J3: 2029E | K3: 2030E | L3: Terminal | M3: Source / Notes
A4: FMP analyst consensus: 2026E – 2030E (5 years) | User estimates required from: N/AE onwards
A6: SECTION 1 — PROJECTION ASSUMPTIONS (darker blue = FMP consensus-derived | lighter blue = user input)
A7: Revenue Growth % | B7: — | C7: ='P&L'!C5/'P&L'!B5-1 | D7: ='P&L'!D5/'P&L'!C5-1 | E7: ='P&L'!E5/'P&L'!D5-1 | F7: ='P&L'!F5/'P&L'!E5-1 | G7: 0.0243 | H7: 0.0135 | I7: 0.0554 | J7: =I7 | K7: =I7 | L7: 0.03 | M7: Yrs 1-3: FMP analyst consensus implied growth (back-calc from rev estimates). Yrs 4-5: formula = Yr 3 growth. Terminal = long-run growth (2-4%).
A8: EBITDA Margin % | B8: ='P&L'!B12/'P&L'!B5 | C8: ='P&L'!C12/'P&L'!C5 | D8: ='P&L'!D12/'P&L'!D5 | E8: ='P&L'!E12/'P&L'!E5 | F8: ='P&L'!F12/'P&L'!F5 | G8: 0.3578 | H8: 0.3578 | I8: 0.3578 | J8: =I8 | K8: =I8 | L8: 0.3901 | M8: Yrs 1-3: FMP analyst consensus margin. Yrs 4-5: = Yr 3 margin. Terminal: long-run normalised EBITDA margin (user input).
A9: D&A as % of Revenue | B9: ='P&L'!B14/'P&L'!B5 | C9: ='P&L'!C14/'P&L'!C5 | D9: ='P&L'!D14/'P&L'!D5 | E9: ='P&L'!E14/'P&L'!E5 | F9: ='P&L'!F14/'P&L'!F5 | G9: =AVERAGE(B9:F9) | H9: =G9 | I9: =G9 | J9: =G9 | K9: =G9 | L9: =G9 | M9: Historical linked from P&L. Yr 1 = avg of historicals; Yrs 2-5 & terminal = Yr 1.
A10: CapEx as % of Revenue | B10: =-'Cash Flow'!B6/'P&L'!B5 | C10: =-'Cash Flow'!C6/'P&L'!C5 | D10: =-'Cash Flow'!D6/'P&L'!D5 | E10: =-'Cash Flow'!E6/'P&L'!E5 | F10: =-'Cash Flow'!F6/'P&L'!F5 | G10: =AVERAGE(B10:F10) | H10: =G10 | I10: =G10 | J10: =G10 | K10: =G10 | L10: =G10 | M10: Historical linked from Cash Flow. Yr 1 = avg of historicals; Yrs 2-5 & terminal = Yr 1.
A11: Change in NWC as % of Revenue | B11: — | C11: =(('Balance Sheet'!C9-'Balance Sheet'!C21)-('Balance Sheet'!B9-'Balance Sheet'!B21))/'P&L'!C5 | D11: =(('Balance Sheet'!D9-'Balance Sheet'!D21)-('Balance Sheet'!C9-'Balance Sheet'!C21))/'P&L'!D5 | E11: =(('Balance Sheet'!E9-'Balance Sheet'!E21)-('Balance Sheet'!D9-'Balance Sheet'!D21))/'P&L'!E5 | F11: =(('Balance Sheet'!F9-'Balance Sheet'!F21)-('Balance Sheet'!E9-'Balance Sheet'!E21))/'P&L'!F5 | G11: =MAX(-0.02,MIN(0.05,AVERAGE(C11:F11))) | H11: =G11*4/5 | I11: =G11*3/5 | J11: =G11*2/5 | K11: =G11*1/5 | L11: 0 | M11: Yr 1 = clamped avg of historicals [-2%, +5%]. Yrs 2-5 fade linearly to 0. Terminal = 0 (steady-state: NWC tracks revenue).
A12: Effective Tax Rate | B12: =IFERROR(MAX(0,MIN(0.5,'P&L'!B22/'P&L'!B21)),0) | C12: =IFERROR(MAX(0,MIN(0.5,'P&L'!C22/'P&L'!C21)),0) | D12: =IFERROR(MAX(0,MIN(0.5,'P&L'!D22/'P&L'!D21)),0) | E12: =IFERROR(MAX(0,MIN(0.5,'P&L'!E22/'P&L'!E21)),0) | F12: =IFERROR(MAX(0,MIN(0.5,'P&L'!F22/'P&L'!F21)),0) | G12: =AVERAGE(B12:F12) | H12: =G12 | I12: =G12 | J12: =G12 | K12: =G12 | L12: =G12 | M12: Historical linked from P&L (tax / pretax income). Forecast: avg of historicals, constant thereafter.
A14: SECTION 2 — REVENUE & EBITDA ($mm)
A15: Revenue | B15: ='P&L'!B5 | C15: ='P&L'!C5 | D15: ='P&L'!D5 | E15: ='P&L'!E5 | F15: ='P&L'!F5 | G15: 49105.5 | H15: 49768.6 | I15: 52524 | J15: =I15*(1+J7) | K15: =J15*(1+K7) | L15: =K15*(1+L7) | M15: FMP consensus years: analyst revenue average ($mm). Range: Low–High shown below. User years: prior × (1+growth).
A16: Analyst Range: Low — High ($mm) | G16: 48,518 — 50,569 | H16: 48,552 — 53,232 | I16: 52,433 — 52,615 | J16: 52,703 — 56,526 | K16: 55,776 — 59,821 | L16: — | M16: Sell-side analyst low / high revenue estimates for consensus years
A17: Number of Analysts | G17: 14 | H17: 15 | I17: 11 | J17: 5 | K17: 5 | L17: — | M17: Red < 5 analysts — treat estimate with caution. Orange < 10.
A18: YoY Revenue Growth % | B18: — | C18: =IFERROR(C15/B15-1,"") | D18: =IFERROR(D15/C15-1,"") | E18: =IFERROR(E15/D15-1,"") | F18: =IFERROR(F15/E15-1,"") | G18: =IFERROR(G15/F15-1,"") | H18: =IFERROR(H15/G15-1,"") | I18: =IFERROR(I15/H15-1,"") | J18: =IFERROR(J15/I15-1,"") | K18: =IFERROR(K15/J15-1,"") | L18: =L7 | M18: =this year / prior year − 1 (formula cross-check on assumptions)
A20: EBITDA | B20: ='P&L'!B12 | C20: ='P&L'!C12 | D20: ='P&L'!D12 | E20: ='P&L'!E12 | F20: ='P&L'!F12 | G20: 17571.6 | H20: 17808.9 | I20: 18794.9 | J20: =J15*J8 | K20: =K15*K8 | L20: =L15*L8 | M20: FMP consensus years: analyst EBITDA average. User years: Revenue × EBITDA margin assumption.
A21: Analyst Range: Low — High ($mm) | G21: 17,361 — 18,095 | H21: 17,373 — 19,048 | I21: 18,762 — 18,827 | J21: 18,859 — 20,227 | K21: 19,959 — 21,406 | L21: — | M21: Sell-side analyst low / high EBITDA estimates for consensus years
A22: EBITDA Margin % | B22: =IFERROR(B20/B15,"") | C22: =IFERROR(C20/C15,"") | D22: =IFERROR(D20/D15,"") | E22: =IFERROR(E20/E15,"") | F22: =IFERROR(F20/F15,"") | G22: =IFERROR(G20/G15,"") | H22: =IFERROR(H20/H15,"") | I22: =IFERROR(I20/I15,"") | ... L22: =IFERROR(L20/L15,"") | M22: =EBITDA / Revenue (formula — cross-check on margin assumption)
A24: SECTION 3 — UNLEVERED FREE CASH FLOW BUILD ($mm)
A25: Less: D&A | B25: =-'P&L'!B14 | C25: =-'P&L'!C14 | D25: =-'P&L'!D14 | E25: =-'P&L'!E14 | F25: =-'P&L'!F14 | G25: =-G15*G9 | H25: =-H15*H9 | I25: =-I15*I9 | J25: =-J15*J9 | K25: =-K15*K9 | L25: =-L15*L9 | M25: =Revenue × D&A % assumption (negative = P&L charge)
A26: EBIT (Operating Profit) | B26: =B20+B25 | C26: =C20+C25 | D26: =D20+D25 | E26: =E20+E25 | F26: =F20+F25 | G26: =G20+G25 | H26: =H20+H25 | I26: =I20+I25 | ... L26: =L20+L25 | M26: =EBITDA + D&A (GAAP operating income, EBIT)
A27: Less: Tax on EBIT (unlevered) | B27: =-B26*B12 | C27: =-C26*C12 | D27: =-D26*D12 | E27: =-E26*E12 | F27: =-F26*F12 | G27: =-G26*G12 | H27: =-H26*H12 | I27: =-I26*I12 | ... L27: =-L26*L12 | M27: =EBIT × tax rate (no interest tax shield — UFCF is pre-debt)
A28: NOPAT | B28: =B26+B27 | C28: =C26+C27 | D28: =D26+D27 | E28: =E26+E27 | F28: =F26+F27 | G28: =G26+G27 | H28: =H26+H27 | I28: =I26+I27 | ... L28: =L26+L27 | M28: =EBIT × (1 − tax rate)
A29: (+) D&A add-back (non-cash) | B29: =-B25 | C29: =-C25 | D29: =-D25 | E29: =-E25 | F29: =-F25 | G29: =-G25 | H29: =-H25 | I29: =-I25 | ... L29: =-L25 | M29: =D&A added back (non-cash charge — converts NOPAT to cash basis)
A30: (−) Capital Expenditures | B30: ='Cash Flow'!B6 | C30: ='Cash Flow'!C6 | D30: ='Cash Flow'!D6 | E30: ='Cash Flow'!E6 | F30: ='Cash Flow'!F6 | G30: =-G15*G10 | H30: =-H15*H10 | I30: =-I15*I10 | J30: =-J15*J10 | K30: =-K15*K10 | L30: =-L15*L10 | M30: =Revenue × CapEx % assumption (negative = cash outflow)
A31: (−) Increase in Net Working Capital | C31: =-(('Balance Sheet'!C9-'Balance Sheet'!C21)-('Balance Sheet'!B9-'Balance Sheet'!B21)) | D31: =-(('Balance Sheet'!D9-'Balance Sheet'!D21)-('Balance Sheet'!C9-'Balance Sheet'!C21)) | E31: =-(('Balance Sheet'!E9-'Balance Sheet'!E21)-('Balance Sheet'!D9-'Balance Sheet'!D21)) | F31: =-(('Balance Sheet'!F9-'Balance Sheet'!F21)-('Balance Sheet'!E9-'Balance Sheet'!E21)) | G31: =-G15*G11 | H31: =-H15*H11 | I31: =-I15*I11 | J31: =-J15*J11 | K31: =-K15*K11 | L31: =-L15*L11 | M31: =−Revenue × NWC% (positive NWC% → cash outflow, reduces UFCF)
A32: UNLEVERED FREE CASH FLOW (UFCF) | B32: =B28+B29+B30+B31 | C32: =C28+C29+C30+C31 | D32: =D28+D29+D30+D31 | E32: =E28+E29+E30+E31 | F32: =F28+F29+F30+F31 | G32: =G28+G29+G30+G31 | H32: =H28+H29+H30+H31 | I32: =I28+I29+I30+I31 | ... L32: =L28+L29+L30+L31 | M32: =NOPAT + D&A − CapEx − ΔNWC (pre-debt, pre-interest free cash flow)
A33: UFCF Margin % | B33: =B32/B15 | C33: =C32/C15 | D33: =D32/D15 | E33: =E32/E15 | F33: =F32/F15 | G33: =IFERROR(G32/G15,"") | H33: =IFERROR(H32/H15,"") | I33: =IFERROR(I32/I15,"") | J33: =IFERROR(J32/J15,"") | K33: =IFERROR(K32/K15,"") | L33: =IFERROR(L32/L15,"") | M33: Sense check — should approximate EBITDA margin less capex intensity
A35: SECTION 4 — TERMINAL VALUE ($mm)
A36: WACC (from WACC tab) | B36: =WACC!B44 | M36: Auto-linked from WACC tab selected output. Override manually if needed.
A37: Terminal Growth Rate (g) | B37: 0.025 | M37: Growth tier: LOW (3.7% 3yr avg rev growth). Bear 2.00% / Base 2.5% / Bull 3.00%. Keep below WACC.
A38: Terminal EV/EBITDA Multiple (exit multiple method) | B38: 15.4 | M38: Growth tier: LOW (3.7% 3yr avg rev growth). Bear 12x / Base 15x / Bull 18x. Override manually if needed.
A40: Terminal Year UFCF (grown by g) | B40: =L32 | M40: Cross-ref from Section 3 — terminal year UFCF (already grown by g in assumptions)
A41: Terminal Value [Gordon Growth: UFCF / (WACC − g)] | B41: =B40/(B36-B37) | M41: Sensitive to g — always cross-check vs Exit Multiple below
A42: Terminal Value [Exit Multiple: Terminal EBITDA × Multiple] | B42: =L20*B38 | M42: Anchored to observable market multiples — less model-sensitive than Gordon Growth
A44: SECTION 5 — DISCOUNTING & ENTERPRISE VALUE ($mm)
A45: Discount Period (mid-year convention) | G45: 0.5 | H45: 1.5 | I45: 2.5 | J45: 3.5 | K45: 4.5 | L45: 5 | M45: Mid-year: 0.5, 1.5, 2.5... assumes FCF received evenly through each year
A46: Discount Factor = 1 / (1 + WACC) ^ period | G46: =1/(1+B36)^G45 | H46: =1/(1+B36)^H45 | I46: =1/(1+B36)^I45 | J46: =1/(1+B36)^J45 | K46: =1/(1+B36)^K45 | L46: =1/(1+B36)^L45 | M46: =1 / (1 + WACC) ^ discount period
A47: PV of UFCF | G47: =G32*G46 | H47: =H32*H46 | I47: =I32*I46 | J47: =J32*J46 | K47: =K32*K46 | M47: =UFCF × discount factor
A48: Sum of PV of FCFs (explicit period) | B48: =G47+H47+I47+J47+K47 | M48: Sum of 5 discounted annual FCFs
A49: PV of Terminal Value [Gordon Growth] | B49: =B41*L46 | M49: Terminal value × terminal-year discount factor
A50: PV of Terminal Value [Exit Multiple] | B50: =B42*L46 | M50: Terminal value × terminal-year discount factor
A52: SECTION 6 — EQUITY VALUE BRIDGE & IMPLIED SHARE PRICE
A53: Enterprise Value [Gordon Growth] | B53: =B48+B49
A54: Enterprise Value [Exit Multiple] | B54: =B48+B50
A55: Less: Net Debt (Debt − Cash) | B55: ='Balance Sheet'!F81 | M55: Linked from Balance Sheet: Total Debt (ST+LT) − Cash & Equivalents (negative = net cash)
A56: Less: Minority Interest | B56: 2106 | M56: Auto-linked from Balance Sheet: minorityInterest
A57: Shares Outstanding — Diluted (mm) | B57: 4313 | M57: Auto-linked: weightedAverageShsOutDil from income statement (diluted)
A59: Implied Share Price [Gordon Growth] ($) | B59: =IFERROR((B53-B55-B56)/B57,"")
A60: Implied Share Price [Exit Multiple] ($) | B60: =IFERROR((B54-B55-B56)/B57,"")
A61: Current Market Price ($) | B61: 81.48 | M61: Auto-linked from FMP company profile — price
A62: Upside / (Downside) [Gordon Growth] | B62: =IFERROR(B59/B61-1,"")
A63: Upside / (Downside) [Exit Multiple] | B63: =IFERROR(B60/B61-1,"")

Sheet Scorecard
A1: JS SCORECARD — KO | Master Prompt v2 | 27 May 2026 | Sector bucket: Stable Compounder
A2: Blue rows = auto-scored (FMP data + yfinance proxies). Yellow rows = manual — select tier from dropdown in column E. Only 2 criteria require manual input: Business Clarity + Long-Term Potential. Score: HIGH=10 | MOD-HIGH=7 | MOD-LOW=3 | LOW=0
A4: ✓ No floor cap (D/EBITDA and EBIT/Interest within safe thresholds)
A6: CRITERION | B6: PART | C6: WEIGHT % | D6: CALCULATED VALUE | E6: TIER ▼ | F6: SCORE | G6: WTD SCORE | H6: NOTES / COMMENTARY (editable)
A7: PART 1 — BUSINESS QUALITY (qualitative)
A8: Business Clarity | B8: P1 | C8: 0.025 | D8: — user input required | F8: =IF(E8="HIGH",10,IF(E8="MOD-HIGH",7,IF(E8="MOD-LOW",3,IF(E8="LOW",0,"")))) | G8: =IF(F8="",0,C8*F8*10)
A9: Moat Profile | B9: P1 | C9: 0.1 | D9: GM 61.6% ✓ (>40%) | GM trend +3.5% ✓ (>+1pp) | ROIC-WACC +11.2% ✓ (>+5pp) | Rev consistency σ=3.7% ✓ (<8%) [4/4 indicators positive — proxy score] | E9: HIGH | F9: 10 | G9: =IF(F9="",0,C9*F9*10) | H9: GM 61.6% ✓ (>40%) | GM trend +3.5% ✓ (>+1pp) | ROIC-WACC +11.2% ✓ (>+5pp) | Rev consistency σ=3.7% ✓ (<8%) [4/4 indicators positive — proxy score]
A10: Long-Term Potential | B10: P1 | C10: 0.1 | D10: — user input required | F10: =IF(E10="HIGH",10,IF(E10="MOD-HIGH",7,IF(E10="MOD-LOW",3,IF(E10="LOW",0,"")))) | G10: =IF(F10="",0,C10*F10*10)
A11: Management | B11: P1 | C11: 0.075 | D11: ROIC trend +0.2% ✓ (>=-2pp) | GM maintained +3.5% ✓ | Op margin +3.3% ✓ (≥-2pp) | Capital returns HIGH ✓ | Share count -0.1%/yr ✓ (net buyback) | Goodwill/Equity 48% ✗ (<40%) [5/6 indicators positive — proxy score] | E11: MOD-HIGH | F11: 8.33 | G11: =IF(F11="",0,C11*F11*10) | H11: ROIC trend +0.2% ✓ (>=-2pp) | GM maintained +3.5% ✓ | Op margin +3.3% ✓ (≥-2pp) | Capital returns HIGH ✓ | Share count -0.1%/yr ✓ (net buyback) | Goodwill/Equity 48% ✗ (<40%) [5/6 indicators positive — proxy score]
A12: PART 2 — FINANCIAL PERFORMANCE (quantitative)
A13: Revenue 3yr CAGR | B13: P2 | C13: 0.1 | D13: 3.7% | E13: MOD-LOW | F13: 4.38 | G13: =IF(F13="",0,C13*F13*10) | H13: 3.7%
A14: Cash Quality (FCF / Net Income) | B14: P2 | C14: 0.1 | D14: 56% [trend penalty: declined >15pp vs 3yr ago] [through-cycle: 70/30 latest+5yr median, latest 40.4% → smoothed 55.6%] | E14: LOW | F14: 0.62 | G14: =IF(F14="",0,C14*F14*10) | H14: 56% [trend penalty: declined >15pp vs 3yr ago] [through-cycle: 70/30 latest+5yr median, latest 40.4% → smoothed 55.6%]
A15: Capital Returns | B15: P2 | C15: 0.05 | D15: $746mm latest FY — 5yr+ consistent equity-funded [payout 14% of FCF — low, building cash] | E15: HIGH | F15: 10 | G15: =IF(F15="",0,C15*F15*10) | H15: $746mm latest FY — 5yr+ consistent equity-funded [payout 14% of FCF — low, building cash]
A16: ROIC | B16: P2 | C16: 0.075 | D16: 16.5% [QoE: CFO/NI 76% 3yr avg — cash conv weak] | E16: MOD-HIGH | F16: 7.18 | G16: =IF(F16="",0,C16*F16*10) | H16: 16.5% [QoE: CFO/NI 76% 3yr avg — cash conv weak]
A17: PART 3 — RISK PROFILE (quantitative / qualitative)
A18: Credit Risk (D / EBITDA) | B18: P3 | C18: 0.05 | D18: 2.5x [through-cycle: 70/30 latest+5yr median, latest 2.4x → smoothed 2.5x] | E18: MOD-HIGH | F18: 7.92 | G18: =IF(F18="",0,C18*F18*10) | H18: 2.5x [through-cycle: 70/30 latest+5yr median, latest 2.4x → smoothed 2.5x]
A19: Interest Cover (EBIT / Interest) | B19: P3 | C19: 0.075 | D19: 8.3x | E19: MOD-HIGH | F19: 9.16 | G19: =IF(F19="",0,C19*F19*10) | H19: 8.3x
A20: Execution Risk | B20: P3 | C20: 0.05 | D20: Rev growth σ=3.7% | OM trend +2.0%, σ=2.5% [quality = direction + stability] | E20: MOD-HIGH | F20: 6.67 | G20: =IF(F20="",0,C20*F20*10) | H20: Rev growth σ=3.7% | OM trend +2.0%, σ=2.5% [quality = direction + stability]
A21: PART 4 — VALUATION (qualitative / user-supplied market data)
A22: Valuation vs Median (P/E) | B22: P4 | C22: 0.1 | D22: Fwd P/E 24.9x (scoring basis) | 5yr avg 24.9x | DCF-implied 15.3x [ref only — not used as benchmark] [+0% vs benchmark] [trail=7.00 | fwd_pe=24.9x→7.00 | abs=7.0 → blended 40/40/20=7.00] PEG=339.89 (fwd_pe=24.9x / eps_growth=7%) [revision:Modest upgrade expected→+0.25] | E22: MOD-HIGH | F22: 7.25 | G22: =IF(F22="",0,C22*F22*10) | H22: Fwd P/E 24.9x (scoring basis) | 5yr avg 24.9x | DCF-implied 15.3x [ref only — not used as benchmark] [+0% vs benchmark] [trail=7.00 | fwd_pe=24.9x→7.00 | abs=7.0 → blended 40/40/20=7.00] PEG=339.89 (fwd_pe=24.9x / eps_growth=7%) [revision:Modest upgrade expected→+0.25]
A23: Valuation vs Median (P/FCF) | B23: P4 | C23: 0.1 | D23: Current 56.8x | 5yr avg 41.9x | DCF-implied 37.9x [ref only — not used as benchmark] [+36% vs benchmark] [trail=1.73 | fwd_pfcf=64.6x→0.00 | abs=0.0 → blended 40/40/20=0.69] [fcf_yield=1.8% vs rf=4.6% spread=-2.8%→modifier=-0.50] | E23: LOW | F23: 0.19 | G23: =IF(F23="",0,C23*F23*10) | H23: Current 56.8x | 5yr avg 41.9x | DCF-implied 37.9x [ref only — not used as benchmark] [+36% vs benchmark] [trail=1.73 | fwd_pfcf=64.6x→0.00 | abs=0.0 → blended 40/40/20=0.69] [fcf_yield=1.8% vs rf=4.6% spread=-2.8%→modifier=-0.50]
A25: TOTAL SCORE (max = 100.0) | G25: =G8+G9+G10+G11+G13+G14+G15+G16+G18+G19+G20+G22+G23 | H25: No floor cap.
A27: =IF(G25="","Score incomplete — fill qualitative tiers above",IF(G25>=80,"STRONG BUY",IF(G25>=65,"BUY",IF(G25>=50,"HOLD",IF(G25>=35,"REDUCE","SELL")))))
A29: SCORING GUIDE: ≥80 STRONG BUY | 65–79 BUY | 50–64 HOLD | 35–49 REDUCE | <35 SELL || Soft cap (non-banks only): −5pts per 1.0x of D/EBITDA above 3.0x; −4pts per 1.0x of EBIT/Int below 3.0x; min 40 || Banks: gates exempt; P3 uses Equity/Assets (CET1 proxy) instead of D/EBITDA
